pydemy/__init__.py
pydemy/_async_client.py
pydemy/_base_client.py
pydemy/_client.py
pydemy/_exceptions.py
pydemy/models/__init__.py
pydemy/models/_chapter.py
pydemy/models/_course.py
pydemy/models/_course_category.py
pydemy/models/_course_review.py
pydemy/models/_course_subcategory.py
pydemy/models/_lecture.py
pydemy/models/_quiz.py
pydemy/models/_user.py
pydemy/models/_filters/__init__.py
pydemy/models/_filters/course_filters.py
pydemy/models/_filters/review_filters.py
pydemy/models/_mixins/__init__.py
pydemy/models/_mixins/serializers.py
pydemy-0.2.9.dist-info/licenses/LICENSE
pydemy-0.2.9.dist-info/METADATA
pydemy-0.2.9.dist-info/WHEEL
pydemy-0.2.9.dist-info/top_level.txt
pydemy-0.2.9.dist-info/RECORD
