Metadata-Version: 2.4
Name: pydemy
Version: 0.2.9
Summary: A Python library for interacting with the Udemy Affiliate API.
Home-page: https://github.com/robelasefa/pydemy
Author: Robel Asefa
Author-email: Robel Asefa <mertigenet@gmail.com>
License: MIT
Project-URL: Homepage, https://github.com/robelasefa/pydemy
Project-URL: Bug Tracker, https://github.com/robelasefa/pydemy/issues
Keywords: Udemy,API,Courses,Education,Udemy Affiliate API,Course Finder,Online Learning,Udemy Integration,Education API,Course Reviews,Learning Platform,Affiliate Marketing,EdTech,Pydantic
Classifier: Development Status :: 3 - Alpha
Classifier: Intended Audience :: Developers
Classifier: Topic :: Education
Classifier: License :: OSI Approved :: MIT License
Classifier: Programming Language :: Python :: 3
Classifier: Programming Language :: Python :: 3.10
Classifier: Programming Language :: Python :: 3.11
Classifier: Programming Language :: Python :: 3.12
Classifier: Operating System :: Microsoft :: Windows
Classifier: Operating System :: POSIX
Classifier: Operating System :: Unix
Classifier: Operating System :: MacOS
Requires-Python: >=3.10
License-File: LICENSE
Requires-Dist: httpx<0.29,>=0.27
Requires-Dist: pydantic<2.11.0,>=2.9.1
Provides-Extra: dev
Requires-Dist: black; extra == "dev"
Requires-Dist: isort; extra == "dev"
Requires-Dist: ruff; extra == "dev"
Dynamic: author
Dynamic: home-page
Dynamic: license-file
